oqtopus/__init__.py
oqtopus/oqtopus.py
oqtopus/oqtopus_plugin.py
oqtopus/core/module.py
oqtopus/core/module_asset.py
oqtopus/core/module_package.py
oqtopus/core/modules_config.py
oqtopus/core/package_prepare_task.py
oqtopus/gui/__init__.py
oqtopus/gui/about_dialog.py
oqtopus/gui/database_connection_widget.py
oqtopus/gui/database_create_dialog.py
oqtopus/gui/database_duplicate_dialog.py
oqtopus/gui/logs_widget.py
oqtopus/gui/main_dialog.py
oqtopus/gui/module_selection_widget.py
oqtopus/gui/module_widget.py
oqtopus/gui/parameters_groupbox.py
oqtopus/gui/plugin_widget.py
oqtopus/gui/project_widget.py
oqtopus/gui/settings_dialog.py
oqtopus/ui/__init__.py
oqtopus/ui/about_dialog.ui
oqtopus/ui/database_connection_widget.ui
oqtopus/ui/database_create_dialog.ui
oqtopus/ui/database_duplicate_dialog.ui
oqtopus/ui/logs_widget.ui
oqtopus/ui/main_dialog.ui
oqtopus/ui/module_selection_widget.ui
oqtopus/ui/module_widget.ui
oqtopus/ui/plugin_widget.ui
oqtopus/ui/project_widget.ui
oqtopus/ui/settings_dialog.ui
oqtopus/utils/__init__.py
oqtopus/utils/plugin_utils.py
oqtopus/utils/qt_utils.py
oqtopus/utils/tmmtlogging.py
oqtopus/utils/translation.py
oqtopus-0.2.1.dist-info/licenses/LICENSE
tests/__init__.py
tests/test_plugin_load.py
oqtopus-0.2.1.dist-info/METADATA
oqtopus-0.2.1.dist-info/WHEEL
oqtopus-0.2.1.dist-info/top_level.txt
oqtopus-0.2.1.dist-info/RECORD
