Metadata-Version: 2.4
Name: oqtopus
Version: 0.2.1
Summary: oQtopus : A QGIS module manager that helps you deploy, manage and upgrade your QGIS projects, plugins and associated postgreSQL / PostGIS data model implementations
Author-email: Damiano Lombardi <damiano@opengis.ch>
License:                     GNU GENERAL PUBLIC LICENSE
Requires-Python: >=3.8
License-File: LICENSE
Dynamic: license-file
